coconut_cli/__init__.py
coconut_cli/__main__.py
coconut_cli/lines.json
coconut_cli-0.1.2.dist-info/WHEEL
coconut_cli-0.1.2.dist-info/METADATA
coconut_cli-0.1.2.dist-info/RECORD
