Metadata-Version: 2.1
Name: coconut-cli
Version: 0.1.2
Summary: 
Author: Arpan Pandey
Author-email: arpan@hackersreboot.tech
Requires-Python: >=3.9,<4.0
Classifier: Programming Language :: Python :: 3
Classifier: Programming Language :: Python :: 3.10
Classifier: Programming Language :: Python :: 3.9
Requires-Dist: inquirer (>=3.1.1,<4.0.0)
Requires-Dist: pyfiglet (>=0.8.post1,<0.9)
